kawadi/__init__.py
kawadi/_repo_version.py
kawadi/cli.py
kawadi/text_search.py
kawadi-0.0.2.dist-info/LICENSE
kawadi-0.0.2.dist-info/METADATA
kawadi-0.0.2.dist-info/WHEEL
kawadi-0.0.2.dist-info/entry_points.txt
kawadi-0.0.2.dist-info/top_level.txt
kawadi-0.0.2.dist-info/RECORD
