Metadata-Version: 2.1
Name: kawadi
Version: 0.0.2
Summary: UNKNOWN
Home-page: https://github.com/jdvala/kawadi
Author: Jay Vala
Author-email: jay.vala@msn.com
License: UNKNOWN
Platform: UNKNOWN
Classifier: Development Status :: 5 - Production/Stable
Classifier: Intended Audience :: Developers
Classifier: License :: OSI Approved :: MIT License
Classifier: Operating System :: OS Independent
Classifier: Programming Language :: Python :: 3.7
Classifier: Programming Language :: Python :: 3.8
Classifier: Topic :: Software Development :: Libraries :: Python Modules
Classifier: Topic :: Utilities
Requires-Python: >=3.7.0
License-File: LICENSE
Requires-Dist: strsimpy (==0.2.1)
